dropbot_elisa_analysis/__init__.py
dropbot_elisa_analysis/plot.py
dropbot_elisa_analysis-0.0.post19.dist-info/DESCRIPTION.rst
dropbot_elisa_analysis-0.0.post19.dist-info/METADATA
dropbot_elisa_analysis-0.0.post19.dist-info/RECORD
dropbot_elisa_analysis-0.0.post19.dist-info/WHEEL
dropbot_elisa_analysis-0.0.post19.dist-info/metadata.json
dropbot_elisa_analysis-0.0.post19.dist-info/pbr.json
dropbot_elisa_analysis-0.0.post19.dist-info/top_level.txt
